veto2/__init__.py
veto2/client.py
veto2/decorator.py
veto2/exceptions.py
veto2-0.1.7.dist-info/METADATA
veto2-0.1.7.dist-info/WHEEL
veto2-0.1.7.dist-info/top_level.txt
veto2-0.1.7.dist-info/RECORD
