Metadata-Version: 2.4
Name: veto2
Version: 0.1.7
Summary: Real-time governance and human-in-the-loop approval for AI agents.
Author-email: Veto Team <hello@veto.sh>
Project-URL: Homepage, https://vetoback-production.up.railway.app
Project-URL: Bug Tracker, https://github.com/veto-sh/veto/issues
Classifier: Programming Language :: Python :: 3
Classifier: License :: OSI Approved :: MIT License
Classifier: Operating System :: OS Independent
Classifier: Topic :: Scientific/Engineering :: Artificial Intelligence
Classifier: Intended Audience :: Developers
Requires-Python: >=3.8
Requires-Dist: requests>=2.25.0
